kivy_garden/invisible_magnet/__init__.py
kivy_garden/invisible_magnet/_install.py
kivy_garden/invisible_magnet/_main.py
kivy_garden/invisible_magnet/_pos_and_size.py
kivy_garden/invisible_magnet/_pos_only.py
kivy_garden_invisible_magnet-0.1.1.dist-info/METADATA
kivy_garden_invisible_magnet-0.1.1.dist-info/WHEEL
kivy_garden_invisible_magnet-0.1.1.dist-info/RECORD
