Metadata-Version: 2.1
Name: kivy-garden-invisible-magnet
Version: 0.1.1
Summary: 
License: MIT
Author: Nattōsai Mitō
Author-email: flow4re2c@gmail.com
Requires-Python: >=3.8.1,<4.0.0
Classifier: License :: OSI Approved :: MIT License
Classifier: Programming Language :: Python :: 3
Classifier: Programming Language :: Python :: 3.9
Classifier: Programming Language :: Python :: 3.10
Classifier: Programming Language :: Python :: 3.11
